UART_TX.v
`timescale 1ns / 1ps

module UART_TX (
    input  wire       clk,       // Internal FPGA clock, though not required by UART
    input  wire       rst_n,     // Reset button (active low)
    input  wire       tx_tick,   // From baud_gen: pulses high when it's time to send a bit
    input  wire       tx_start,  // Signal to tell us to start sending, Start bit, usually, pulling the already high signal low
    input  wire [7:0] tx_data,   // The 8 bits of data to send
    output reg        tx_out,    // The actual serial wire going to the other device receiver(rx)
    output reg        tx_done    // Stop signal pull back high
);

    //State Machine states
    localparam IDLE  = 2'b00;  // Remembers when in Idle state
    localparam START = 2'b01;  // Remembers when Starting transmission
    localparam DATA  = 2'b10;  // Remembers when DATA is being sent
    localparam STOP  = 2'b11;  // Remembers when Stopping transmission

    // Internal hardware registers (memory)
    reg [1:0] state;       // Keeps track of our current state
    reg [7:0] data_reg;    // The shift register holding the data
    reg [2:0] bit_cnt;     // Counts from 0 to 7

    // Always block: Describing hardware that updates on every clock tick
    // Using "<=" (non-blocking assignment) to update registers as in sequential logic!
   
    always @(posedge clk or negedge rst_n) begin
        if (!rst_n) begin
            // RESET BEHAVIOR, rst_n is always low, !rst_n mean high, so if high What should the hardware do, i.e reset has been pressed
            state   <= IDLE; // Change state to IDLE
            tx_out  <= 1'b1; // UART line is HIGH when idle
            tx_done <= 1'b0; // Set bit to low, not done
            bit_cnt <= 3'd0; // Bit count is 0, not started or at first bit
            data_reg<= 8'd0; // No data sent yet
        end 

	else begin

            // When not in reset. 
            case (state)
                IDLE: 
		    begin
                    tx_out  <= 1'b1; // Keep line HIGH, meaning no data sent
                    tx_done <= 1'b0; // Turn off done, nothing is completed
                    
                    if (tx_start == 1'b1) begin
                        // If start bit is high
                        data_reg <= tx_data;
			state <= START;
                    end
                end

                START: begin
                    // We only move to the next phase when the baud rate generator says so
                    if (tx_tick == 1'b1) begin
                        tx_out <= 1'b0;
                        state <= DATA;
                        bit_cnt <= 3'b0;
                    end
                end

                DATA: begin
                    if (tx_tick == 1'b1) 
		    begin
                        // Send the lowest bit of data_reg to the wire
                        tx_out <= data_reg[0];

                        // Shift the data_reg to the right (put a 0 at the top, keep the bottom 7)
                        data_reg <= {1'b0, data_reg[7:1]};

                        if (bit_cnt == 7) begin
                            state <= STOP;
                        end 
			else begin
                            bit_cnt <= bit_cnt + 1;
                        end
                    end
                end

                STOP: begin
                    if (tx_tick == 1'b1) begin
                        tx_out <= 1'b1;
                        tx_done <= 1'b1;
                        state <= IDLE;
                    end
                end
                
                default: state <= IDLE; // Safety catch
            endcase
        end
    end

endmodule

UART_TX_Testbench.v
`timescale 1ns / 1ps

module UART_TX_Testbench;

// Signals needed in the module
	reg		clk;
	reg		rst_n;
	reg		tx_tick;
	reg		tx_start;
	reg [7:0]	tx_data;
	wire		tx_out;
	wire		tx_done;
// Instantiate the transmitter DUT (Device under test)

	UART_TX uut(
		.clk(clk),
		.rst_n(rst_n),
		.tx_tick(tx_tick),
		.tx_start(tx_start),
		.tx_data(tx_data),
		.tx_out(tx_out),
		.tx_done(tx_done)
	);

	// Generating the clock 

    	always #5 clk = ~clk;

    	//  Generate the Baud Tick
    	// Instead of using the full baud_gen module, we'll just fake a tick every 100 clock cycles 
    	// to make the simulation run faster and easier to read.
    	always begin
        	#990 tx_tick = 1'b1; // Wait 99 clock cycles
        	#10  tx_tick = 1'b0; // Pulse high for 1 clock cycle
    	end

    	//The Main Test Sequence
    	initial begin
        	// Setup GTKWave output files
        	$dumpfile("uart_tx_sim.vcd");
        	$dumpvars(0, UART_TX_Testbench);

        	// Initialize all inputs to 0
        	clk      = 0;
        	rst_n    = 0;
        	tx_tick  = 0;
        	tx_start = 0;
        	tx_data  = 8'h00;

        	// Step 1: Release the Reset button
        	#100;
        	rst_n = 1;
        	#100;

        	// Step 2: Send a Byte! Let's send 8'hAB (Binary: 10101011)
        	// Note: UART sends LSB first, so we should see 1, 1, 0, 1, 0, 1, 0, 1 on the wire.
        	$display("Starting transmission of 0xAB...");
        	tx_data  = 8'hAB;
        	tx_start = 1'b1;
        	#10;             // Hold start button for 1 clock cycle
        	tx_start = 1'b0; // Release start button

        	// Step 3: Wait for the module to say it's done
        	wait (tx_done == 1'b1);
        	$display("Transmission complete!");

        	// Step 4: Wait a little bit, then end the simulation
        	#500;
        	$finish;
    	end

endmodule

uart_tx_sim.vcd
$date
	Thu Mar  5 14:31:07 2026
$end
$version
	Icarus Verilog
$end
$timescale
	1ps
$end
$scope module UART_TX_Testbench $end
$var wire 1 ! tx_out $end
$var wire 1 " tx_done $end
$var reg 1 # clk $end
$var reg 1 $ rst_n $end
$var reg 8 % tx_data [7:0] $end
$var reg 1 & tx_start $end
$var reg 1 ' tx_tick $end
$scope module uut $end
$var wire 1 # clk $end
$var wire 1 $ rst_n $end
$var wire 8 ( tx_data [7:0] $end
$var wire 1 & tx_start $end
$var wire 1 ' tx_tick $end
$var parameter 2 ) DATA $end
$var parameter 2 * IDLE $end
$var parameter 2 + START $end
$var parameter 2 , STOP $end
$var reg 3 - bit_cnt [2:0] $end
$var reg 8 . data_reg [7:0] $end
$var reg 2 / state [1:0] $end
$var reg 1 " tx_done $end
$var reg 1 ! tx_out $end
$upscope $end
$upscope $end
$enddefinitions $end
$comment Show the parameter values. $end
$dumpall
b11 ,
b1 +
b0 *
b10 )
$end
#0
$dumpvars
b0 /
b0 .
b0 -
b0 (
0'
0&
b0 %
0$
0#
0"
1!
$end
#5000
1#
#10000
0#
#15000
1#
#20000
0#
#25000
1#
#30000
0#
#35000
1#
#40000
0#
#45000
1#
#50000
0#
#55000
1#
#60000
0#
#65000
1#
#70000
0#
#75000
1#
#80000
0#
#85000
1#
#90000
0#
#95000
1#
#100000
0#
1$
#105000
1#
#110000
0#
#115000
1#
#120000
0#
#125000
1#
#130000
0#
#135000
1#
#140000
0#
#145000
1#
#150000
0#
#155000
1#
#160000
0#
#165000
1#
#170000
0#
#175000
1#
#180000
0#
#185000
1#
#190000
0#
#195000
1#
#200000
0#
1&
b10101011 %
b10101011 (
#205000
b1 /
b10101011 .
1#
#210000
0#
0&
#215000
1#
#220000
0#
#225000
1#
#230000
0#
#235000
1#
#240000
0#
#245000
1#
#250000
0#
#255000
1#
#260000
0#
#265000
1#
#270000
0#
#275000
1#
#280000
0#
#285000
1#
#290000
0#
#295000
1#
#300000
0#
#305000
1#
#310000
0#
#315000
1#
#320000
0#
#325000
1#
#330000
0#
#335000
1#
#340000
0#
#345000
1#
#350000
0#
#355000
1#
#360000
0#
#365000
1#
#370000
0#
#375000
1#
#380000
0#
#385000
1#
#390000
0#
#395000
1#
#400000
0#
#405000
1#
#410000
0#
#415000
1#
#420000
0#
#425000
1#
#430000
0#
#435000
1#
#440000
0#
#445000
1#
#450000
0#
#455000
1#
#460000
0#
#465000
1#
#470000
0#
#475000
1#
#480000
0#
#485000
1#
#490000
0#
#495000
1#
#500000
0#
#505000
1#
#510000
0#
#515000
1#
#520000
0#
#525000
1#
#530000
0#
#535000
1#
#540000
0#
#545000
1#
#550000
0#
#555000
1#
#560000
0#
#565000
1#
#570000
0#
#575000
1#
#580000
0#
#585000
1#
#590000
0#
#595000
1#
#600000
0#
#605000
1#
#610000
0#
#615000
1#
#620000
0#
#625000
1#
#630000
0#
#635000
1#
#640000
0#
#645000
1#
#650000
0#
#655000
1#
#660000
0#
#665000
1#
#670000
0#
#675000
1#
#680000
0#
#685000
1#
#690000
0#
#695000
1#
#700000
0#
#705000
1#
#710000
0#
#715000
1#
#720000
0#
#725000
1#
#730000
0#
#735000
1#
#740000
0#
#745000
1#
#750000
0#
#755000
1#
#760000
0#
#765000
1#
#770000
0#
#775000
1#
#780000
0#
#785000
1#
#790000
0#
#795000
1#
#800000
0#
#805000
1#
#810000
0#
#815000
1#
#820000
0#
#825000
1#
#830000
0#
#835000
1#
#840000
0#
#845000
1#
#850000
0#
#855000
1#
#860000
0#
#865000
1#
#870000
0#
#875000
1#
#880000
0#
#885000
1#
#890000
0#
#895000
1#
#900000
0#
#905000
1#
#910000
0#
#915000
1#
#920000
0#
#925000
1#
#930000
0#
#935000
1#
#940000
0#
#945000
1#
#950000
0#
#955000
1#
#960000
0#
#965000
1#
#970000
0#
#975000
1#
#980000
0#
#985000
1#
#990000
0#
1'
#995000
b10 /
0!
1#
#1000000
0#
0'
